{
  "frontmatter": {
    "gameid": 1407209,
    "matchnum": "4004",
    "date": "2026-05-01",
    "league": "欧罗巴联赛",
    "home": "诺丁汉森林",
    "away": "阿斯顿维拉",
    "kickoff_cst": "2026-05-01 03:00",
    "spf": {
      "win": "6.20",
      "draw": "4.40",
      "lost": "1.35"
    },
    "asia_main": {
      "handicap": "平手降",
      "home_water": "0.890↓",
      "away_water": "0.770↑",
      "company": "威**尔"
    },
    "euro_main": {
      "win": "2.28",
      "draw": "3.00",
      "lost": "2.80",
      "company": "竞*官*"
    },
    "fetched_at_utc": "2026-04-30T10:20:08Z"
  },
  "shuju": {
    "title": "诺丁汉森林VS阿斯顿维拉(2025/2026欧罗巴)-数据分析-500彩票网",
    "h2h_summary": "双方近 6 次交战，诺丁汉森林 2胜 1平 3负 ，进9球，失11球，大球4次，小球2次",
    "team_ranks": [
      "诺丁汉森林 [欧罗巴]",
      "阿斯顿维拉 [欧罗巴]"
    ],
    "h2h_rows": [
      {
        "赛事": "英超",
        "比赛日期": "2026-04-12",
        "主队 比分 客队": "[16] 诺丁汉森林 1 : 1 阿斯顿维拉 [4]",
        "半场": "1 : 1",
        "赛果": "平",
        "": "0.99 平手/半球 0.85",
        "盘路": "输",
        "大小": "小",
        "备注": "-"
      },
      {
        "赛事": "英超",
        "比赛日期": "2026-01-03",
        "主队 比分 客队": "[3] 阿斯顿维拉 3: 1 诺丁汉森林 [17]",
        "半场": "1: 0",
        "赛果": "负",
        "": "0.92 半球 0.92",
        "盘路": "输",
        "大小": "大",
        "备注": "-"
      },
      {
        "赛事": "英超",
        "比赛日期": "2025-04-06",
        "主队 比分 客队": "[7] 阿斯顿维拉 2: 1 诺丁汉森林 [3]",
        "半场": "2: 0",
        "赛果": "负",
        "": "0.83 平手/半球 1.03",
        "盘路": "输",
        "大小": "大",
        "备注": "-"
      },
      {
        "赛事": "英超",
        "比赛日期": "2024-12-15",
        "主队 比分 客队": "[5] 诺丁汉森林 2 :1 阿斯顿维拉 [6]",
        "半场": "0 : 0",
        "赛果": "胜",
        "": "0.9 平手 0.96",
        "盘路": "赢",
        "大小": "大",
        "备注": "-"
      },
      {
        "赛事": "英超",
        "比赛日期": "2024-02-24",
        "主队 比分 客队": "[4] 阿斯顿维拉 4: 2 诺丁汉森林 [16]",
        "半场": "3: 1",
        "赛果": "负",
        "": "0.92 一球 0.94",
        "盘路": "输",
        "大小": "大",
        "备注": "-"
      },
      {
        "赛事": "英超",
        "比赛日期": "2023-11-05",
        "主队 比分 客队": "[16] 诺丁汉森林 2 :0 阿斯顿维拉 [5]",
        "半场": "1 :0",
        "赛果": "胜",
        "": "0.94 受半球 0.92",
        "盘路": "赢",
        "大小": "小",
        "备注": "-"
      }
    ],
    "recent_form": {
      "home": {
        "team": "诺丁汉森林",
        "summary": "诺丁汉森林 近10场战绩 5胜 4平 1负 进 19球 失 7球",
        "matches": [
          {
            "赛事": "英超",
            "比赛日期": "26-04-25",
            "主队 比分 客队": "桑德兰 0: 5 诺丁汉森林",
            "盘口": "0",
            "半场": "0: 4",
            "赛果": "胜",
            "盘路": "赢",
            "大小": "大"
          },
          {
            "赛事": "英超",
            "比赛日期": "26-04-19",
            "主队 比分 客队": "诺丁汉森林 4 :1 伯恩利",
            "盘口": "-1.25",
            "半场": "0 :1",
            "赛果": "胜",
            "盘路": "赢",
            "大小": "大"
          },
          {
            "赛事": "欧罗巴",
            "比赛日期": "26-04-17",
            "主队 比分 客队": "诺丁汉森林 1 :0 波尔图",
            "盘口": "-0.25",
            "半场": "1 :0",
            "赛果": "胜",
            "盘路": "赢",
            "大小": "小"
          },
          {
            "赛事": "英超",
            "比赛日期": "26-04-12",
            "主队 比分 客队": "诺丁汉森林 1 : 1 阿斯顿维拉",
            "盘口": "-0.25",
            "半场": "1 : 1",
            "赛果": "平",
            "盘路": "输",
            "大小": "小"
          },
          {
            "赛事": "欧罗巴",
            "比赛日期": "26-04-10",
            "主队 比分 客队": "波尔图 1 : 1 诺丁汉森林",
            "盘口": "-0.5",
            "半场": "1 : 1",
            "赛果": "平",
            "盘路": "赢",
            "大小": "小"
          },
          {
            "赛事": "英超",
            "比赛日期": "26-03-22",
            "主队 比分 客队": "热刺 0: 3 诺丁汉森林",
            "盘口": "-0.25",
            "半场": "0: 1",
            "赛果": "胜",
            "盘路": "赢",
            "大小": "大"
          },
          {
            "赛事": "欧罗巴",
            "比赛日期": "26-03-20",
            "主队 比分 客队": "中日德兰 1: 2 诺丁汉森林",
            "盘口": "0",
            "半场": "0: 1",
            "赛果": "胜",
            "盘路": "赢",
            "大小": "大"
          },
          {
            "赛事": "英超",
            "比赛日期": "26-03-15",
            "主队 比分 客队": "诺丁汉森林 0 : 0 富勒姆",
            "盘口": "-0.25",
            "半场": "0 : 0",
            "赛果": "平",
            "盘路": "输",
            "大小": "小"
          },
          {
            "赛事": "欧罗巴",
            "比赛日期": "26-03-13",
            "主队 比分 客队": "诺丁汉森林 0 :1 中日德兰",
            "盘口": "-1",
            "半场": "0 : 0",
            "赛果": "负",
            "盘路": "输",
            "大小": "小"
          },
          {
            "赛事": "英超",
            "比赛日期": "26-03-05",
            "主队 比分 客队": "曼城 2 : 2 诺丁汉森林",
            "盘口": "-1.25",
            "半场": "1: 0",
            "赛果": "平",
            "盘路": "赢",
            "大小": "大"
          }
        ]
      },
      "away": {
        "team": "阿斯顿维拉",
        "summary": "阿斯顿维拉 近10场战绩 6胜 1平 3负 进 19球 失 11球",
        "matches": [
          {
            "赛事": "英超",
            "比赛日期": "26-04-25",
            "主队 比分 客队": "富勒姆 1: 0 阿斯顿维拉",
            "盘口": "0",
            "半场": "1: 0",
            "赛果": "负",
            "盘路": "输",
            "大小": "小"
          },
          {
            "赛事": "英超",
            "比赛日期": "26-04-19",
            "主队 比分 客队": "阿斯顿维拉 4 :3 桑德兰",
            "盘口": "-0.75",
            "半场": "2 :1",
            "赛果": "胜",
            "盘路": "赢",
            "大小": "大"
          },
          {
            "赛事": "欧罗巴",
            "比赛日期": "26-04-17",
            "主队 比分 客队": "阿斯顿维拉 4 :0 博洛尼亚",
            "盘口": "-1",
            "半场": "3 :0",
            "赛果": "胜",
            "盘路": "赢",
            "大小": "大"
          },
          {
            "赛事": "英超",
            "比赛日期": "26-04-12",
            "主队 比分 客队": "诺丁汉森林 1 : 1 阿斯顿维拉",
            "盘口": "-0.25",
            "半场": "1 : 1",
            "赛果": "平",
            "盘路": "赢",
            "大小": "小"
          },
          {
            "赛事": "欧罗巴",
            "比赛日期": "26-04-10",
            "主队 比分 客队": "博洛尼亚 1: 3 阿斯顿维拉",
            "盘口": "0.5",
            "半场": "0: 1",
            "赛果": "胜",
            "盘路": "赢",
            "大小": "大"
          },
          {
            "赛事": "球会友谊",
            "比赛日期": "26-03-27",
            "主队 比分 客队": "阿斯顿维拉 1 :2 埃尔切",
            "盘口": "",
            "半场": "1 : 1",
            "赛果": "负",
            "盘路": "-",
            "大小": "大"
          },
          {
            "赛事": "英超",
            "比赛日期": "26-03-22",
            "主队 比分 客队": "阿斯顿维拉 2 :0 西汉姆联",
            "盘口": "-0.75",
            "半场": "1 :0",
            "赛果": "胜",
            "盘路": "赢",
            "大小": "小"
          },
          {
            "赛事": "欧罗巴",
            "比赛日期": "26-03-20",
            "主队 比分 客队": "阿斯顿维拉 2 :0 里尔",
            "盘口": "-0.75",
            "半场": "0 : 0",
            "赛果": "胜",
            "盘路": "赢",
            "大小": "小"
          },
          {
            "赛事": "英超",
            "比赛日期": "26-03-15",
            "主队 比分 客队": "曼联 3: 1 阿斯顿维拉",
            "盘口": "-0.75",
            "半场": "0 : 0",
            "赛果": "负",
            "盘路": "输",
            "大小": "大"
          },
          {
            "赛事": "欧罗巴",
            "比赛日期": "26-03-13",
            "主队 比分 客队": "里尔 0: 1 阿斯顿维拉",
            "盘口": "0.25",
            "半场": "0 : 0",
            "赛果": "胜",
            "盘路": "赢",
            "大小": "小"
          }
        ]
      }
    },
    "future_fixtures": {
      "home": [
        {
          "赛事": "英超",
          "比赛日期": "2026-05-04",
          "主队 客队": "切尔西 VS 诺丁汉森林",
          "相隔": "3天"
        },
        {
          "赛事": "欧罗巴",
          "比赛日期": "2026-05-08",
          "主队 客队": "阿斯顿维拉 VS 诺丁汉森林",
          "相隔": "7天"
        },
        {
          "赛事": "英超",
          "比赛日期": "2026-05-10",
          "主队 客队": "诺丁汉森林 VS 纽卡斯尔联",
          "相隔": "9天"
        },
        {
          "赛事": "英超",
          "比赛日期": "2026-05-17",
          "主队 客队": "曼联 VS 诺丁汉森林",
          "相隔": "16天"
        },
        {
          "赛事": "英超",
          "比赛日期": "2026-05-24",
          "主队 客队": "诺丁汉森林 VS 伯恩茅斯",
          "相隔": "23天"
        }
      ],
      "away": [
        {
          "赛事": "英超",
          "比赛日期": "2026-05-04",
          "主队 客队": "阿斯顿维拉 VS 热刺",
          "相隔": "3天"
        },
        {
          "赛事": "欧罗巴",
          "比赛日期": "2026-05-08",
          "主队 客队": "阿斯顿维拉 VS 诺丁汉森林",
          "相隔": "7天"
        },
        {
          "赛事": "英超",
          "比赛日期": "2026-05-10",
          "主队 客队": "伯恩利 VS 阿斯顿维拉",
          "相隔": "9天"
        },
        {
          "赛事": "英超",
          "比赛日期": "2026-05-17",
          "主队 客队": "阿斯顿维拉 VS 利物浦",
          "相隔": "16天"
        },
        {
          "赛事": "英超",
          "比赛日期": "2026-05-24",
          "主队 客队": "曼城 VS 阿斯顿维拉",
          "相隔": "23天"
        }
      ]
    },
    "lineup": {
      "home": {
        "formation": null,
        "starters": [
          {
            "number": "11",
            "name": "克里斯·伍德",
            "position": "前锋"
          },
          {
            "number": "19",
            "name": "伊戈尔·热苏斯",
            "position": "前锋"
          },
          {
            "number": "10",
            "name": "吉布斯·怀特",
            "position": "中场"
          },
          {
            "number": "8",
            "name": "埃利奥特·安德森",
            "position": "中场"
          },
          {
            "number": "6",
            "name": "易卜拉希马·桑加雷",
            "position": "中场"
          },
          {
            "number": "21",
            "name": "奥马里·哈钦森",
            "position": "中场"
          },
          {
            "number": "3",
            "name": "内科·威廉姆斯",
            "position": "后卫"
          },
          {
            "number": "23",
            "name": "雅伊尔·库尼亚",
            "position": "后卫"
          },
          {
            "number": "31",
            "name": "尼古拉·米伦科维奇",
            "position": "后卫"
          },
          {
            "number": "34",
            "name": "奥拉·埃纳",
            "position": "后卫"
          },
          {
            "number": "26",
            "name": "马茨·瑟尔斯",
            "position": "守门员"
          }
        ],
        "subs": [
          {
            "number": "9",
            "name": "塔伊沃·阿沃尼伊",
            "position": "前锋"
          },
          {
            "number": "29",
            "name": "迪莱内·巴克瓦",
            "position": "前锋"
          },
          {
            "number": "24",
            "name": "詹姆斯·麦卡蒂",
            "position": "中场"
          },
          {
            "number": "22",
            "name": "赖恩·耶茨",
            "position": "中场"
          },
          {
            "number": "16",
            "name": "尼古拉斯·多明格斯",
            "position": "中场"
          },
          {
            "number": "14",
            "name": "丹·恩多耶",
            "position": "前锋"
          },
          {
            "number": "25",
            "name": "卢卡·内茨",
            "position": "后卫"
          },
          {
            "number": "4",
            "name": "费利佩·莫拉托",
            "position": "后卫"
          },
          {
            "number": "27",
            "name": "斯特凡·奥尔特加",
            "position": "守门员"
          }
        ],
        "injured": [],
        "suspended": []
      },
      "away": {
        "formation": null,
        "starters": [
          {
            "number": "11",
            "name": "奥列尔·沃特金斯",
            "position": "前锋"
          },
          {
            "number": "10",
            "name": "埃米利亚诺·布恩迪亚",
            "position": "中场"
          },
          {
            "number": "27",
            "name": "摩根·罗杰斯",
            "position": "中场"
          },
          {
            "number": "7",
            "name": "约翰·麦金",
            "position": "中场"
          },
          {
            "number": "8",
            "name": "尤里·蒂勒曼斯",
            "position": "中场"
          },
          {
            "number": "26",
            "name": "拉马尔·博加德",
            "position": "中场"
          },
          {
            "number": "12",
            "name": "卢卡斯·迪涅",
            "position": "后卫"
          },
          {
            "number": "14",
            "name": "保·托雷斯",
            "position": "后卫"
          },
          {
            "number": "4",
            "name": "伊兹里·孔萨",
            "position": "后卫"
          },
          {
            "number": "2",
            "name": "马蒂·卡什",
            "position": "后卫"
          },
          {
            "number": "23",
            "name": "达米安·埃米利亚诺·马丁内斯",
            "position": "守门员"
          }
        ],
        "subs": [
          {
            "number": "19",
            "name": "杰登·桑乔",
            "position": "前锋"
          },
          {
            "number": "31",
            "name": "利昂·贝利",
            "position": "前锋"
          },
          {
            "number": "21",
            "name": "道格拉斯·路易斯",
            "position": "中场"
          },
          {
            "number": "22",
            "name": "伊恩·马特森",
            "position": "后卫"
          },
          {
            "number": "6",
            "name": "罗斯·巴克利",
            "position": "中场"
          },
          {
            "number": "5",
            "name": "泰隆·明斯",
            "position": "后卫"
          },
          {
            "number": "3",
            "name": "维克托·林德洛夫",
            "position": "后卫"
          },
          {
            "number": "40",
            "name": "马尔科·比佐特",
            "position": "守门员"
          },
          {
            "number": "18",
            "name": "塔米·亚伯拉罕",
            "position": "前锋"
          }
        ],
        "injured": [],
        "suspended": []
      }
    }
  },
  "yazhi": [
    {
      "cid": "293",
      "company": "威**尔",
      "live": {
        "home_water": "0.890↓",
        "handicap": "平手降",
        "away_water": "0.770↑",
        "time": "04-30 16:49"
      },
      "init": {
        "home_water": "0.990",
        "handicap": "平手/半球",
        "away_water": "0.670",
        "time": "04-17 18:22"
      }
    },
    {
      "cid": "5",
      "company": "*门",
      "live": {
        "home_water": "0.940↑",
        "handicap": "平手",
        "away_water": "0.840↓",
        "time": "04-30 15:08"
      },
      "init": {
        "home_water": "0.790",
        "handicap": "平手",
        "away_water": "0.990",
        "time": "04-25 16:07"
      }
    },
    {
      "cid": "2",
      "company": "立*",
      "live": {
        "home_water": "1.400↑",
        "handicap": "半球",
        "away_water": "0.500↓",
        "time": "04-28 05:07"
      },
      "init": {
        "home_water": "1.370",
        "handicap": "半球",
        "away_water": "0.530",
        "time": "04-17 09:23"
      }
    },
    {
      "cid": "3",
      "company": "**t3*5",
      "live": {
        "home_water": "0.970↑",
        "handicap": "平手",
        "away_water": "0.870↓",
        "time": "04-30 18:14"
      },
      "init": {
        "home_water": "0.780",
        "handicap": "平手",
        "away_water": "1.100",
        "time": "04-17 16:24"
      }
    },
    {
      "cid": "4",
      "company": "I***rw**t*n",
      "live": {
        "home_water": "0.900↑",
        "handicap": "平手",
        "away_water": "0.850↓",
        "time": "04-30 13:19"
      },
      "init": {
        "home_water": "0.770",
        "handicap": "平手",
        "away_water": "0.950",
        "time": "04-19 22:08"
      }
    },
    {
      "cid": "280",
      "company": "*冠",
      "live": {
        "home_water": "1.030↓",
        "handicap": "平手降",
        "away_water": "0.850↑",
        "time": "04-30 18:11"
      },
      "init": {
        "home_water": "1.090",
        "handicap": "平手/半球",
        "away_water": "0.790",
        "time": "04-17 17:20"
      }
    },
    {
      "cid": "9",
      "company": "易*博",
      "live": {
        "home_water": "1.220↑",
        "handicap": "平手/半球升",
        "away_water": "0.600↓",
        "time": "04-30 17:58"
      },
      "init": {
        "home_water": "0.850",
        "handicap": "平手",
        "away_water": "0.990",
        "time": "04-25 01:50"
      }
    },
    {
      "cid": "1484",
      "company": "on**",
      "live": {
        "home_water": "1.040↑",
        "handicap": "平手",
        "away_water": "0.900↓",
        "time": "04-30 17:17"
      },
      "init": {
        "home_water": "0.870",
        "handicap": "平手",
        "away_water": "1.070",
        "time": "04-17 05:44"
      }
    },
    {
      "cid": "6",
      "company": "伟*",
      "live": {
        "home_water": "0.780↓",
        "handicap": "受平手/半球降",
        "away_water": "1.120↑",
        "time": "04-30 17:43"
      },
      "init": {
        "home_water": "1.090",
        "handicap": "平手/半球",
        "away_water": "0.750",
        "time": "04-17 07:25"
      }
    },
    {
      "cid": "1055",
      "company": "Pi****le平*",
      "live": {
        "home_water": "1.040↓",
        "handicap": "平手降",
        "away_water": "0.870↑",
        "time": "04-30 17:19"
      },
      "init": {
        "home_water": "1.100",
        "handicap": "平手/半球",
        "away_water": "0.780",
        "time": "04-17 15:01"
      }
    },
    {
      "cid": "651",
      "company": "利*",
      "live": {
        "home_water": "1.030↓",
        "handicap": "平手降",
        "away_water": "0.890↑",
        "time": "04-30 17:27"
      },
      "init": {
        "home_water": "1.040",
        "handicap": "平手/半球",
        "away_water": "0.800",
        "time": "04-17 17:21"
      }
    },
    {
      "cid": "140",
      "company": "M****on88 (明*)",
      "live": {
        "home_water": "1.060↓",
        "handicap": "平手降",
        "away_water": "0.860↑",
        "time": "04-30 17:34"
      },
      "init": {
        "home_water": "1.070",
        "handicap": "平手/半球",
        "away_water": "0.790",
        "time": "04-17 15:02"
      }
    },
    {
      "cid": "122",
      "company": "香**会",
      "live": {
        "home_water": "0.980↓",
        "handicap": "平手降",
        "away_water": "0.840↑",
        "time": "04-30 16:01"
      },
      "init": {
        "home_water": "1.070",
        "handicap": "平手/半球",
        "away_water": "0.720",
        "time": "04-28 14:23"
      }
    },
    {
      "cid": "502",
      "company": "12**t (壹*博)",
      "live": {
        "home_water": "1.050↓",
        "handicap": "平手降",
        "away_water": "0.870↑",
        "time": "04-30 17:34"
      },
      "init": {
        "home_water": "1.160",
        "handicap": "平手/半球",
        "away_water": "0.720",
        "time": "04-18 15:18"
      }
    },
    {
      "cid": "863",
      "company": "18**t",
      "live": {
        "home_water": "0.960↓",
        "handicap": "平手降",
        "away_water": "0.850↑",
        "time": "04-30 18:02"
      },
      "init": {
        "home_water": "1.020",
        "handicap": "平手/半球",
        "away_water": "0.740",
        "time": "04-17 15:01"
      }
    },
    {
      "cid": "537",
      "company": "W****t (盈*)",
      "live": {
        "home_water": "1.050↓",
        "handicap": "平手降",
        "away_water": "0.850↑",
        "time": "04-30 17:46"
      },
      "init": {
        "home_water": "1.070",
        "handicap": "平手/半球",
        "away_water": "0.810",
        "time": "04-17 17:50"
      }
    }
  ],
  "ouzhi": [
    {
      "cid": "1",
      "company": "竞*官*",
      "time": "2026-04-30 18:02:17",
      "odds": {
        "live": [
          "2.28",
          "3.00",
          "2.80"
        ],
        "init": [
          "2.70",
          "3.08",
          "2.30"
        ]
      },
      "prob": {
        "live": [
          "38.85%",
          "29.52%",
          "31.63%"
        ],
        "init": [
          "32.78%",
          "28.74%",
          "38.48%"
        ]
      },
      "ret": {
        "live": [
          "88.57%"
        ],
        "init": [
          "88.51%"
        ]
      },
      "kelly": {
        "live": [
          "0.78",
          "0.88",
          "1.02"
        ],
        "init": [
          "0.93",
          "0.90",
          "0.84"
        ]
      }
    },
    {
      "cid": "293",
      "company": "威**尔",
      "time": "2026-04-30 16:41:30",
      "odds": {
        "live": [
          "2.40",
          "3.20",
          "2.88"
        ],
        "init": [
          "2.75",
          "3.10",
          "2.50"
        ]
      },
      "prob": {
        "live": [
          "38.71%",
          "29.03%",
          "32.26%"
        ],
        "init": [
          "33.48%",
          "29.70%",
          "36.83%"
        ]
      },
      "ret": {
        "live": [
          "92.90%"
        ],
        "init": [
          "92.06%"
        ]
      },
      "kelly": {
        "live": [
          "0.82",
          "0.94",
          "1.05"
        ],
        "init": [
          "0.94",
          "0.91",
          "0.91"
        ]
      }
    },
    {
      "cid": "5",
      "company": "*门",
      "time": "2026-04-30 11:14:07",
      "odds": {
        "live": [
          "2.33",
          "3.20",
          "2.60"
        ],
        "init": [
          "2.52",
          "3.20",
          "2.40"
        ]
      },
      "prob": {
        "live": [
          "38.11%",
          "27.75%",
          "34.15%"
        ],
        "init": [
          "35.24%",
          "27.75%",
          "37.00%"
        ]
      },
      "ret": {
        "live": [
          "88.79%"
        ],
        "init": [
          "88.81%"
        ]
      },
      "kelly": {
        "live": [
          "0.80",
          "0.94",
          "0.95"
        ],
        "init": [
          "0.87",
          "0.94",
          "0.87"
        ]
      }
    },
    {
      "cid": "2",
      "company": "立*",
      "time": "2026-04-30 16:05:57",
      "odds": {
        "live": [
          "2.40",
          "3.30",
          "2.87"
        ],
        "init": [
          "2.70",
          "3.30",
          "2.60"
        ]
      },
      "prob": {
        "live": [
          "39.01%",
          "28.37%",
          "32.62%"
        ],
        "init": [
          "35.01%",
          "28.64%",
          "36.35%"
        ]
      },
      "ret": {
        "live": [
          "93.62%"
        ],
        "init": [
          "94.52%"
        ]
      },
      "kelly": {
        "live": [
          "0.82",
          "0.96",
          "1.05"
        ],
        "init": [
          "0.93",
          "0.96",
          "0.95"
        ]
      }
    },
    {
      "cid": "3",
      "company": "**t3*5",
      "time": "2026-04-30 17:26:48",
      "odds": {
        "live": [
          "2.40",
          "3.25",
          "2.90"
        ],
        "init": [
          "2.80",
          "3.30",
          "2.60"
        ]
      },
      "prob": {
        "live": [
          "38.97%",
          "28.78%",
          "32.25%"
        ],
        "init": [
          "34.18%",
          "29.00%",
          "36.81%"
        ]
      },
      "ret": {
        "live": [
          "93.53%"
        ],
        "init": [
          "95.71%"
        ]
      },
      "kelly": {
        "live": [
          "0.82",
          "0.95",
          "1.06"
        ],
        "init": [
          "0.96",
          "0.96",
          "0.95"
        ]
      }
    },
    {
      "cid": "4",
      "company": "I***rw**t*n",
      "time": "2026-04-30 13:19:09",
      "odds": {
        "live": [
          "2.55",
          "3.30",
          "2.80"
        ],
        "init": [
          "2.70",
          "3.25",
          "2.70"
        ]
      },
      "prob": {
        "live": [
          "37.27%",
          "28.80%",
          "33.94%"
        ],
        "init": [
          "35.33%",
          "29.35%",
          "35.33%"
        ]
      },
      "ret": {
        "live": [
          "95.03%"
        ],
        "init": [
          "95.38%"
        ]
      },
      "kelly": {
        "live": [
          "0.88",
          "0.96",
          "1.02"
        ],
        "init": [
          "0.93",
          "0.95",
          "0.98"
        ]
      }
    },
    {
      "cid": "8",
      "company": "S**I",
      "time": "2026-04-30 16:29:48",
      "odds": {
        "live": [
          "2.35",
          "3.40",
          "2.80"
        ],
        "init": [
          "2.85",
          "3.25",
          "2.65"
        ]
      },
      "prob": {
        "live": [
          "39.52%",
          "27.31%",
          "33.17%"
        ],
        "init": [
          "33.87%",
          "29.70%",
          "36.43%"
        ]
      },
      "ret": {
        "live": [
          "92.87%"
        ],
        "init": [
          "96.53%"
        ]
      },
      "kelly": {
        "live": [
          "0.81",
          "0.99",
          "1.02"
        ],
        "init": [
          "0.98",
          "0.95",
          "0.97"
        ]
      }
    },
    {
      "cid": "280",
      "company": "*冠",
      "time": "2026-04-30 17:32:11",
      "odds": {
        "live": [
          "2.42",
          "3.60",
          "2.85"
        ],
        "init": [
          "2.85",
          "3.30",
          "2.56"
        ]
      },
      "prob": {
        "live": [
          "39.66%",
          "26.66%",
          "33.68%"
        ],
        "init": [
          "33.59%",
          "29.01%",
          "37.40%"
        ]
      },
      "ret": {
        "live": [
          "95.98%"
        ],
        "init": [
          "95.74%"
        ]
      },
      "kelly": {
        "live": [
          "0.83",
          "1.05",
          "1.04"
        ],
        "init": [
          "0.98",
          "0.96",
          "0.93"
        ]
      }
    },
    {
      "cid": "9",
      "company": "易*博",
      "time": "2026-04-30 17:53:24",
      "odds": {
        "live": [
          "2.38",
          "3.10",
          "2.60"
        ],
        "init": [
          "2.70",
          "3.20",
          "2.60"
        ]
      },
      "prob": {
        "live": [
          "37.27%",
          "28.61%",
          "34.12%"
        ],
        "init": [
          "34.70%",
          "29.27%",
          "36.03%"
        ]
      },
      "ret": {
        "live": [
          "88.70%"
        ],
        "init": [
          "93.68%"
        ]
      },
      "kelly": {
        "live": [
          "0.82",
          "0.91",
          "0.95"
        ],
        "init": [
          "0.93",
          "0.94",
          "0.95"
        ]
      }
    },
    {
      "cid": "6",
      "company": "伟*",
      "time": "2026-04-30 17:42:05",
      "odds": {
        "live": [
          "2.38",
          "3.20",
          "2.80"
        ],
        "init": [
          "2.88",
          "3.25",
          "2.40"
        ]
      },
      "prob": {
        "live": [
          "38.55%",
          "28.67%",
          "32.77%"
        ],
        "init": [
          "32.40%",
          "28.71%",
          "38.88%"
        ]
      },
      "ret": {
        "live": [
          "91.76%"
        ],
        "init": [
          "93.32%"
        ]
      },
      "kelly": {
        "live": [
          "0.82",
          "0.94",
          "1.02"
        ],
        "init": [
          "0.99",
          "0.95",
          "0.87"
        ]
      }
    },
    {
      "cid": "11",
      "company": "B**n",
      "time": "2026-04-30 16:06:49",
      "odds": {
        "live": [
          "2.40",
          "3.40",
          "2.87"
        ],
        "init": [
          "2.70",
          "3.30",
          "2.60"
        ]
      },
      "prob": {
        "live": [
          "39.34%",
          "27.77%",
          "32.90%"
        ],
        "init": [
          "35.01%",
          "28.64%",
          "36.35%"
        ]
      },
      "ret": {
        "live": [
          "94.41%"
        ],
        "init": [
          "94.52%"
        ]
      },
      "kelly": {
        "live": [
          "0.82",
          "0.99",
          "1.05"
        ],
        "init": [
          "0.93",
          "0.96",
          "0.95"
        ]
      }
    },
    {
      "cid": "1055",
      "company": "Pi****le平*",
      "time": "2026-04-30 17:18:57",
      "odds": {
        "live": [
          "2.42",
          "3.35",
          "2.96"
        ],
        "init": [
          "2.88",
          "3.25",
          "2.65"
        ]
      },
      "prob": {
        "live": [
          "39.37%",
          "28.44%",
          "32.19%"
        ],
        "init": [
          "33.64%",
          "29.81%",
          "36.56%"
        ]
      },
      "ret": {
        "live": [
          "95.28%"
        ],
        "init": [
          "96.87%"
        ]
      },
      "kelly": {
        "live": [
          "0.83",
          "0.98",
          "1.08"
        ],
        "init": [
          "0.99",
          "0.95",
          "0.97"
        ]
      }
    },
    {
      "cid": "16",
      "company": "10**t",
      "time": "2026-04-30 17:00:47",
      "odds": {
        "live": [
          "2.50",
          "3.30",
          "2.80"
        ],
        "init": [
          "2.80",
          "3.30",
          "2.60"
        ]
      },
      "prob": {
        "live": [
          "37.73%",
          "28.58%",
          "33.69%"
        ],
        "init": [
          "34.18%",
          "29.00%",
          "36.81%"
        ]
      },
      "ret": {
        "live": [
          "94.32%"
        ],
        "init": [
          "95.71%"
        ]
      },
      "kelly": {
        "live": [
          "0.86",
          "0.96",
          "1.02"
        ],
        "init": [
          "0.96",
          "0.96",
          "0.95"
        ]
      }
    },
    {
      "cid": "14",
      "company": "C***l",
      "time": "2026-04-30 09:13:39",
      "odds": {
        "live": [
          "2.50",
          "3.40",
          "2.70"
        ],
        "init": [
          "2.60",
          "3.30",
          "2.70"
        ]
      },
      "prob": {
        "live": [
          "37.58%",
          "27.63%",
          "34.79%"
        ],
        "init": [
          "36.35%",
          "28.64%",
          "35.01%"
        ]
      },
      "ret": {
        "live": [
          "93.94%"
        ],
        "init": [
          "94.52%"
        ]
      },
      "kelly": {
        "live": [
          "0.86",
          "0.99",
          "0.98"
        ],
        "init": [
          "0.89",
          "0.96",
          "0.98"
        ]
      }
    },
    {
      "cid": "651",
      "company": "利*",
      "time": "2026-04-30 17:53:07",
      "odds": {
        "live": [
          "2.27",
          "3.14",
          "2.76"
        ],
        "init": [
          "2.72",
          "3.25",
          "2.58"
        ]
      },
      "prob": {
        "live": [
          "39.29%",
          "28.40%",
          "32.31%"
        ],
        "init": [
          "34.59%",
          "28.95%",
          "36.46%"
        ]
      },
      "ret": {
        "live": [
          "89.18%"
        ],
        "init": [
          "94.08%"
        ]
      },
      "kelly": {
        "live": [
          "0.78",
          "0.92",
          "1.01"
        ],
        "init": [
          "0.93",
          "0.95",
          "0.94"
        ]
      }
    },
    {
      "cid": "291",
      "company": "U****t (优*客)",
      "time": "2026-04-30 12:56:08",
      "odds": {
        "live": [
          "2.45",
          "3.35",
          "2.85"
        ],
        "init": [
          "2.70",
          "3.25",
          "2.63"
        ]
      },
      "prob": {
        "live": [
          "38.60%",
          "28.23%",
          "33.18%"
        ],
        "init": [
          "35.00%",
          "29.07%",
          "35.93%"
        ]
      },
      "ret": {
        "live": [
          "94.56%"
        ],
        "init": [
          "94.49%"
        ]
      },
      "kelly": {
        "live": [
          "0.84",
          "0.98",
          "1.04"
        ],
        "init": [
          "0.93",
          "0.95",
          "0.96"
        ]
      }
    },
    {
      "cid": "275",
      "company": "S***t**g**t (博*堂)",
      "time": "2026-04-30 16:08:52",
      "odds": {
        "live": [
          "2.40",
          "3.40",
          "2.87"
        ],
        "init": [
          "2.70",
          "3.30",
          "2.60"
        ]
      },
      "prob": {
        "live": [
          "39.34%",
          "27.77%",
          "32.90%"
        ],
        "init": [
          "35.01%",
          "28.64%",
          "36.35%"
        ]
      },
      "ret": {
        "live": [
          "94.41%"
        ],
        "init": [
          "94.52%"
        ]
      },
      "kelly": {
        "live": [
          "0.82",
          "0.99",
          "1.05"
        ],
        "init": [
          "0.93",
          "0.96",
          "0.95"
        ]
      }
    },
    {
      "cid": "127",
      "company": "IBC**t (沙*)",
      "time": "2026-04-30 17:54:06",
      "odds": {
        "live": [
          "2.31",
          "3.20",
          "2.65"
        ],
        "init": [
          "2.85",
          "3.30",
          "2.53"
        ]
      },
      "prob": {
        "live": [
          "38.56%",
          "27.83%",
          "33.61%"
        ],
        "init": [
          "33.44%",
          "28.88%",
          "37.67%"
        ]
      },
      "ret": {
        "live": [
          "89.07%"
        ],
        "init": [
          "95.31%"
        ]
      },
      "kelly": {
        "live": [
          "0.79",
          "0.94",
          "0.97"
        ],
        "init": [
          "0.98",
          "0.96",
          "0.92"
        ]
      }
    },
    {
      "cid": "140",
      "company": "M****on88 (明*)",
      "time": "2026-04-30 17:59:38",
      "odds": {
        "live": [
          "2.32",
          "3.15",
          "2.66"
        ],
        "init": [
          "2.84",
          "3.30",
          "2.53"
        ]
      },
      "prob": {
        "live": [
          "38.33%",
          "28.23%",
          "33.43%"
        ],
        "init": [
          "33.52%",
          "28.85%",
          "37.63%"
        ]
      },
      "ret": {
        "live": [
          "88.93%"
        ],
        "init": [
          "95.20%"
        ]
      },
      "kelly": {
        "live": [
          "0.80",
          "0.92",
          "0.97"
        ],
        "init": [
          "0.97",
          "0.96",
          "0.92"
        ]
      }
    },
    {
      "cid": "122",
      "company": "香**会",
      "time": "2026-04-30 16:03:17",
      "odds": {
        "live": [
          "2.28",
          "3.00",
          "2.77"
        ],
        "init": [
          "2.65",
          "2.90",
          "2.43"
        ]
      },
      "prob": {
        "live": [
          "38.71%",
          "29.42%",
          "31.86%"
        ],
        "init": [
          "33.29%",
          "30.42%",
          "36.30%"
        ]
      },
      "ret": {
        "live": [
          "88.27%"
        ],
        "init": [
          "88.21%"
        ]
      },
      "kelly": {
        "live": [
          "0.78",
          "0.88",
          "1.01"
        ],
        "init": [
          "0.91",
          "0.85",
          "0.89"
        ]
      }
    },
    {
      "cid": "502",
      "company": "12**t (壹*博)",
      "time": "2026-04-30 17:59:51",
      "odds": {
        "live": [
          "2.24",
          "3.20",
          "2.75"
        ],
        "init": [
          "2.84",
          "3.30",
          "2.53"
        ]
      },
      "prob": {
        "live": [
          "39.77%",
          "27.84%",
          "32.39%"
        ],
        "init": [
          "33.52%",
          "28.85%",
          "37.63%"
        ]
      },
      "ret": {
        "live": [
          "89.08%"
        ],
        "init": [
          "95.20%"
        ]
      },
      "kelly": {
        "live": [
          "0.77",
          "0.94",
          "1.00"
        ],
        "init": [
          "0.97",
          "0.96",
          "0.92"
        ]
      }
    },
    {
      "cid": "1487",
      "company": "88******",
      "time": "2026-04-30 16:56:38",
      "odds": {
        "live": [
          "2.40",
          "3.20",
          "2.87"
        ],
        "init": [
          "2.75",
          "3.10",
          "2.60"
        ]
      },
      "prob": {
        "live": [
          "38.67%",
          "29.00%",
          "32.33%"
        ],
        "init": [
          "33.96%",
          "30.12%",
          "35.92%"
        ]
      },
      "ret": {
        "live": [
          "92.80%"
        ],
        "init": [
          "93.39%"
        ]
      },
      "kelly": {
        "live": [
          "0.82",
          "0.94",
          "1.05"
        ],
        "init": [
          "0.94",
          "0.91",
          "0.95"
        ]
      }
    },
    {
      "cid": "1488",
      "company": "大巨*",
      "time": "2026-04-30 13:43:06",
      "odds": {
        "live": [
          "2.55",
          "3.30",
          "2.70"
        ],
        "init": [
          "2.75",
          "3.30",
          "2.70"
        ]
      },
      "prob": {
        "live": [
          "36.80%",
          "28.44%",
          "34.76%"
        ],
        "init": [
          "35.06%",
          "29.22%",
          "35.71%"
        ]
      },
      "ret": {
        "live": [
          "93.85%"
        ],
        "init": [
          "96.43%"
        ]
      },
      "kelly": {
        "live": [
          "0.88",
          "0.96",
          "0.98"
        ],
        "init": [
          "0.94",
          "0.96",
          "0.98"
        ]
      }
    },
    {
      "cid": "18",
      "company": "必*",
      "time": "2026-04-30 17:54:42",
      "odds": {
        "live": [
          "2.42",
          "3.30",
          "2.98"
        ],
        "init": [
          "2.92",
          "3.40",
          "2.72"
        ]
      },
      "prob": {
        "live": [
          "39.29%",
          "28.81%",
          "31.90%"
        ],
        "init": [
          "34.10%",
          "29.29%",
          "36.61%"
        ]
      },
      "ret": {
        "live": [
          "95.07%"
        ],
        "init": [
          "99.58%"
        ]
      },
      "kelly": {
        "live": [
          "0.83",
          "0.96",
          "1.09"
        ],
        "init": [
          "1.00",
          "0.99",
          "0.99"
        ]
      }
    },
    {
      "cid": "863",
      "company": "18**t",
      "time": "2026-04-30 18:11:08",
      "odds": {
        "live": [
          "2.35",
          "3.25",
          "2.85"
        ],
        "init": [
          "2.70",
          "3.30",
          "2.60"
        ]
      },
      "prob": {
        "live": [
          "39.25%",
          "28.38%",
          "32.37%"
        ],
        "init": [
          "35.01%",
          "28.64%",
          "36.35%"
        ]
      },
      "ret": {
        "live": [
          "92.24%"
        ],
        "init": [
          "94.52%"
        ]
      },
      "kelly": {
        "live": [
          "0.81",
          "0.95",
          "1.04"
        ],
        "init": [
          "0.93",
          "0.96",
          "0.95"
        ]
      }
    },
    {
      "cid": "1259",
      "company": "1x**t",
      "time": "2026-04-30 17:29:10",
      "odds": {
        "live": [
          "2.51",
          "3.44",
          "3.07"
        ],
        "init": [
          "2.91",
          "3.33",
          "2.69"
        ]
      },
      "prob": {
        "live": [
          "39.26%",
          "28.64%",
          "32.10%"
        ],
        "init": [
          "33.83%",
          "29.57%",
          "36.60%"
        ]
      },
      "ret": {
        "live": [
          "98.54%"
        ],
        "init": [
          "98.46%"
        ]
      },
      "kelly": {
        "live": [
          "0.86",
          "1.01",
          "1.12"
        ],
        "init": [
          "1.00",
          "0.97",
          "0.98"
        ]
      }
    },
    {
      "cid": "67",
      "company": "**ts**n",
      "time": "2026-04-30 13:43:05",
      "odds": {
        "live": [
          "2.50",
          "3.40",
          "2.90"
        ],
        "init": [
          "2.75",
          "3.30",
          "2.70"
        ]
      },
      "prob": {
        "live": [
          "38.50%",
          "28.31%",
          "33.19%"
        ],
        "init": [
          "35.06%",
          "29.22%",
          "35.71%"
        ]
      },
      "ret": {
        "live": [
          "96.25%"
        ],
        "init": [
          "96.43%"
        ]
      },
      "kelly": {
        "live": [
          "0.86",
          "0.99",
          "1.06"
        ],
        "init": [
          "0.94",
          "0.96",
          "0.98"
        ]
      }
    },
    {
      "cid": "132",
      "company": "I***rt*ps",
      "time": "2026-04-30 17:54:53",
      "odds": {
        "live": [
          "2.35",
          "3.20",
          "2.85"
        ],
        "init": [
          "2.80",
          "3.20",
          "2.60"
        ]
      },
      "prob": {
        "live": [
          "39.08%",
          "28.70%",
          "32.22%"
        ],
        "init": [
          "33.88%",
          "29.64%",
          "36.48%"
        ]
      },
      "ret": {
        "live": [
          "91.84%"
        ],
        "init": [
          "94.85%"
        ]
      },
      "kelly": {
        "live": [
          "0.81",
          "0.94",
          "1.04"
        ],
        "init": [
          "0.96",
          "0.94",
          "0.95"
        ]
      }
    },
    {
      "cid": "350",
      "company": "**t-at-H**e",
      "time": "2026-04-30 17:11:23",
      "odds": {
        "live": [
          "2.40",
          "3.35",
          "2.80"
        ],
        "init": [
          "2.80",
          "3.25",
          "2.65"
        ]
      },
      "prob": {
        "live": [
          "38.86%",
          "27.84%",
          "33.31%"
        ],
        "init": [
          "34.27%",
          "29.52%",
          "36.21%"
        ]
      },
      "ret": {
        "live": [
          "93.26%"
        ],
        "init": [
          "95.95%"
        ]
      },
      "kelly": {
        "live": [
          "0.82",
          "0.98",
          "1.02"
        ],
        "init": [
          "0.96",
          "0.95",
          "0.97"
        ]
      }
    },
    {
      "cid": "772",
      "company": "**tf**g",
      "time": "2026-04-30 17:54:57",
      "odds": {
        "live": [
          "2.50",
          "3.25",
          "2.80"
        ],
        "init": [
          "2.80",
          "3.20",
          "2.60"
        ]
      },
      "prob": {
        "live": [
          "37.56%",
          "28.90%",
          "33.54%"
        ],
        "init": [
          "33.88%",
          "29.64%",
          "36.48%"
        ]
      },
      "ret": {
        "live": [
          "93.91%"
        ],
        "init": [
          "94.85%"
        ]
      },
      "kelly": {
        "live": [
          "0.86",
          "0.95",
          "1.02"
        ],
        "init": [
          "0.96",
          "0.94",
          "0.95"
        ]
      }
    }
  ]
}